orama_utils/__init__.py
orama_utils/date_features.py
orama_utils/holiday_features.py
orama_utils/weather_features.py
orama_utils/holiday_db/__init__.py
orama_utils/holiday_db/spain_holidays.csv
orama_utils/weather_db/__init__.py
orama_utils-0.1.8.dist-info/licenses/LICENSE
orama_utils-0.1.8.dist-info/METADATA
orama_utils-0.1.8.dist-info/WHEEL
orama_utils-0.1.8.dist-info/top_level.txt
orama_utils-0.1.8.dist-info/RECORD
