Metadata-Version: 2.4
Name: orama-utils
Version: 0.1.8
Summary: Utility functions and tools for data processing and analysis
Home-page: https://github.com/Orama-Solutions/utils
Author: Orama Solutions
Author-email: keti@oramasolutions.io
License-Expression: MIT
Project-URL: Homepage, https://github.com/Orama-Solutions/utils
Project-URL: Bug Tracker, https://github.com/Orama-Solutions/utils/issues
Classifier: Programming Language :: Python :: 3
Classifier: Operating System :: OS Independent
Requires-Python: >=3.7
License-File: LICENSE
Requires-Dist: pandas>=1.3.0
Requires-Dist: numpy>=1.20.0
Requires-Dist: boto3>=1.26.0
Provides-Extra: dev
Requires-Dist: pytest>=7.0.0; extra == "dev"
Requires-Dist: pytest-cov>=4.0.0; extra == "dev"
Requires-Dist: black>=23.0.0; extra == "dev"
Requires-Dist: flake8>=6.0.0; extra == "dev"
Requires-Dist: mypy>=1.0.0; extra == "dev"
Dynamic: author-email
Dynamic: home-page
Dynamic: license-file
Dynamic: requires-python
